aeotrade_connector/__init__.py
aeotrade_connector/apps.py
aeotrade_connector/crontab/__init__.py
aeotrade_connector/db/__init__.py
aeotrade_connector/db/choices.py
aeotrade_connector/db/signals.py
aeotrade_connector/decorators.py
aeotrade_connector/encoders.py
aeotrade_connector/exceptions.py
aeotrade_connector/helpers.py
aeotrade_connector/http_client/__init__.py
aeotrade_connector/http_client/async_client.py
aeotrade_connector/http_client/sync_client.py
aeotrade_connector/management/commands/initconnector.py
aeotrade_connector/management/commands/startconnector.py
aeotrade_connector/mgirations/__init__.py
aeotrade_connector/migrations/0001_initial.py
aeotrade_connector/migrations/__init__.py
aeotrade_connector/models.py
aeotrade_connector/mq/__init__.py
aeotrade_connector/mq/base.py
aeotrade_connector/mq/distribute.py
aeotrade_connector/mq/manager.py
aeotrade_connector/mq/rabbitmq/__init__.py
aeotrade_connector/mq/rabbitmq/client.py
aeotrade_connector/schemas/__init__.py
aeotrade_connector/schemas/common.py
aeotrade_connector/schemas/connector_services.py
aeotrade_connector/serializers.py
aeotrade_connector/services.py
aeotrade_connector/simple_cache.py
aeotrade_connector/startup.py
aeotrade_connector/template_test/__init__.py-tpl
aeotrade_connector/template_test/admin.py-tpl
aeotrade_connector/template_test/apps.py-tpl
aeotrade_connector/template_test/models.py-tpl
aeotrade_connector/template_test/tests.py-tpl
aeotrade_connector/template_test/urls.py-tpl
aeotrade_connector/template_test/views.py
aeotrade_connector/templates/app_tpl/__init__.py-tpl
aeotrade_connector/templates/app_tpl/apps.py-tpl
aeotrade_connector/templates/app_tpl/services.py-tpl
aeotrade_connector/templates/app_tpl/tasks.py-tpl
aeotrade_connector/templates/app_tpl/views.py-tpl
aeotrade_connector/templates/proj_tpl/connector_views.py
aeotrade_connector/templates/proj_tpl/dispatcher.tpl
aeotrade_connector/templates/proj_tpl/init_urls.tpl
aeotrade_connector/templates/proj_tpl/init_views.tpl
django_aeotrade_connector-0.1.1.dist-info/METADATA
django_aeotrade_connector-0.1.1.dist-info/WHEEL
django_aeotrade_connector-0.1.1.dist-info/RECORD
