Metadata-Version: 2.1
Name: django-aeotrade-connector
Version: 0.1.1
Summary: A connector development framework adapted to Django
Author: hero
Author-email: wanghao@aeotrade.com
Requires-Python: >=3.10,<4
Classifier: Programming Language :: Python :: 3
Classifier: Programming Language :: Python :: 3.10
Classifier: Programming Language :: Python :: 3.11
Classifier: Programming Language :: Python :: 3.12
Requires-Dist: aio-pika (>=9.5.3,<10.0.0)
Requires-Dist: aiohttp (>=3.11.10,<4.0.0)
Requires-Dist: django-apscheduler (>=0.7.0,<0.8.0)
Requires-Dist: django-redis (>=5.4.0,<6.0.0)
Requires-Dist: djangorestframework (>=3.15.2,<4.0.0)
Requires-Dist: httpx (>=0.28.1,<0.29.0)
Requires-Dist: pydantic (>=2.10.3,<3.0.0)
Requires-Dist: requests (>=2.32.3,<3.0.0)
Requires-Dist: xmltodict (>=0.14.2,<0.15.0)
